CodeBase/__init__.py
CodeBase/try.py
MasonPypiSample/__init__.py
MasonPypiSample/module.py
MasonPypiSample/try.py
MasonPypiSample-0.2.dist-info/LICENSE.txt
MasonPypiSample-0.2.dist-info/METADATA
MasonPypiSample-0.2.dist-info/WHEEL
MasonPypiSample-0.2.dist-info/top_level.txt
MasonPypiSample-0.2.dist-info/RECORD
