Metadata-Version: 2.1
Name: MasonPypiSample
Version: 0.2
Summary: Mason pypi example
Home-page: https://github.com/NS47000/PypiSampleCode
Author: Mason
Author-email: maocheng101@gmail.com
Classifier: Programming Language :: Python :: 3
Classifier: License :: OSI Approved :: MIT License
Classifier: Operating System :: OS Independent
Requires-Python: >=3.6
License-File: LICENSE.txt
